<?xml version="1.0" encoding="utf-8"?>
<resources>
    <color name="green">#FF45B25C</color>
    <color name="green_alpha_10">#1A45B25C</color>

    <color name="orange">#FFEA8736</color>
    <color name="orange_alpha_10">#1AEA8736</color>
    <color name="orange_alpha_20">#33EA8736</color>

    <color name="red">#FFFF0000</color>
    <color name="red_alpha_10">#1AFF0000</color>

    <color name="black">#FF000000</color>
    <color name="gray_600">#FF333333</color>
    <color name="gray_400">#FF666666</color>
    <color name="gray_300">#FF777777</color>
    <color name="gray_100">#FFC2C2C2</color>
    <color name="gray_80">#FFEAE8E8</color>
    <color name="gray_50">#FFF6F6F6</color>
    <color name="gray_600_alpha_30">#4D333333</color>

    <color name="white">#FFFFFFFF</color>
    <color name="white_alpha_30">#4DFFFFFF</color>
    <color name="white_alpha_75">#BFFFFFFF</color>
</resources>